robotu_molkit/__init__.py
robotu_molkit/cli.py
robotu_molkit/config.py
robotu_molkit/constants.py
robotu_molkit/credentials_manager.py
robotu_molkit/molecule.py
robotu_molkit/robotu_molkit.py
robotu_molkit/test_summary.py
robotu_molkit/ai/__init__.py
robotu_molkit/ai/base.py
robotu_molkit/ai/granite.py
robotu_molkit/ingest/__init__.py
robotu_molkit/ingest/api_clients.py
robotu_molkit/ingest/parsers.py
robotu_molkit/ingest/workers.py
robotu_molkit/search/embedding_client.py
robotu_molkit/search/index_manager.py
robotu_molkit/search/searcher.py
robotu_molkit/utils/__init__.py
robotu_molkit/utils/utils.py
robotu_molkit/vector/__init__.py
robotu_molkit/vector/summary_generator.py
robotu_molkit/vector/watsonx_index.py
robotu_molkit/vector/prompts/default/general_prompt.txt
robotu_molkit/vector/prompts/default/general_vars.json
robotu_molkit/vector/prompts/default/materials_prompt.txt
robotu_molkit/vector/prompts/default/pharma_prompt.txt
robotu_molkit/vector/prompts/default/safety_prompt.txt
robotu_molkit/vector/prompts/default/spectra_prompt.txt
robotu_molkit-0.1.5.dist-info/licenses/AUTHORS.rst
robotu_molkit-0.1.5.dist-info/licenses/LICENSE
robotu_molkit-0.1.5.dist-info/METADATA
robotu_molkit-0.1.5.dist-info/WHEEL
robotu_molkit-0.1.5.dist-info/entry_points.txt
robotu_molkit-0.1.5.dist-info/top_level.txt
robotu_molkit-0.1.5.dist-info/RECORD
