Metadata-Version: 2.4
Name: robotu-molkit
Version: 0.1.5
Summary: Quantum-ready molecular toolkit. An open-source Python library that pulls PubChem records, structures them into Molecule objects with rich property sets, and enriches each with IBM Granite summaries and embeddings—ready for quantum simulations, AI pipelines, and scientific research.
Author-email: Robotu <tech@robotu.ai>
Maintainer-email: Carlos Murillo <tech@robotu.ai>
License: Apache-2.0
Project-URL: Homepage, https://robotu.ai
Project-URL: Issues, https://github.com/carlosamurillo/robotu_molkit/issues
Project-URL: Changelog, https://github.com/carlosamurillo/robotu_molkit/blob/main/HISTORY.rst
Classifier: Development Status :: 3 - Alpha
Classifier: Intended Audience :: Science/Research
Classifier: License :: OSI Approved :: Apache Software License
Classifier: Programming Language :: Python :: 3
Classifier: Topic :: Scientific/Engineering :: Chemistry
Requires-Python: >=3.11
License-File: LICENSE
License-File: AUTHORS.rst
Requires-Dist: aiohttp==3.11.18
Requires-Dist: aiolimiter==1.2.1
Requires-Dist: faiss-cpu==1.11.0
Requires-Dist: ibm_watsonx_ai==1.3.13
Requires-Dist: numpy==2.2.5
Requires-Dist: pubchempy==1.0.4
Requires-Dist: pydantic==2.11.4
Requires-Dist: rdkit==2024.9.6
Requires-Dist: requests==2.32.3
Requires-Dist: typer==0.15.3
Provides-Extra: dev
Requires-Dist: bump2version==0.5.11; extra == "dev"
Requires-Dist: cmake==4.0.0; extra == "dev"
Requires-Dist: coverage==4.5.4; extra == "dev"
Requires-Dist: pytest==6.2.4; extra == "dev"
Requires-Dist: readme_renderer==43.0; extra == "dev"
Requires-Dist: ruff==0.3.5; extra == "dev"
Requires-Dist: Sphinx==7.2.6; extra == "dev"
Requires-Dist: tox==3.14.0; extra == "dev"
Requires-Dist: twine==5.0.0; extra == "dev"
Requires-Dist: virtualenv==20.30.0; extra == "dev"
Requires-Dist: watchdog==0.9.0; extra == "dev"
Dynamic: license-file
